PlayfairCipher/PlayfairCipher.py
PlayfairCipher/__init__.py
playfairpolycipher-0.1.dist-info/License.txt
playfairpolycipher-0.1.dist-info/METADATA
playfairpolycipher-0.1.dist-info/WHEEL
playfairpolycipher-0.1.dist-info/top_level.txt
playfairpolycipher-0.1.dist-info/RECORD
