Metadata-Version: 2.1
Name: playfairpolycipher
Version: 0.1
Summary: A Python library for the Playfair Cipher
Home-page: https://github.com/Fluffy-debuger/poly_playfair_cipher
Author: Fluffy_Debuger,SiddheshGanesh
Author-email: a69247199@gmail.com
Classifier: Programming Language :: Python :: 3
Classifier: License :: OSI Approved :: MIT License
Classifier: Operating System :: OS Independent
Requires-Python: >=3.6
License-File: License.txt
